komanawa/kendall_stats/__init__.py
komanawa/kendall_stats/example_data.py
komanawa/kendall_stats/mann_kendall.py
komanawa/kendall_stats/multi_part_kendall.py
komanawa/kendall_stats/time_test_check_step_window_results.txt
komanawa/kendall_stats/time_test_results.txt
komanawa/kendall_stats/time_tests.py
komanawa/kendall_stats/time_tests_check_step_window.py
komanawa/kendall_stats/utils.py
komanawa/kendall_stats/version.py
komanawa_kendall_stats-2.0.3.dist-info/licenses/LICENSE
komanawa_kendall_stats-2.0.3.dist-info/METADATA
komanawa_kendall_stats-2.0.3.dist-info/WHEEL
komanawa_kendall_stats-2.0.3.dist-info/top_level.txt
komanawa_kendall_stats-2.0.3.dist-info/RECORD
