Metadata-Version: 2.4
Name: komanawa-kendall-stats
Version: 2.0.3
Summary: A package to calculate Mann Kendall statistics and implment Mulipart Mann Kendall tests
Author-email: Matt Dumont <Matt@komanawa.com>
License:                    GNU LESSER GENERAL PUBLIC LICENSE
Project-URL: Homepage, https://github.com/Komanawa-Solutions-Ltd/komanawa-kendall-stats
Project-URL: Issues, https://github.com/Komanawa-Solutions-Ltd/komanawa-kendall-stats/issues
Project-URL: Documentation, https://komanawa-solutions-ltd.github.io/komanawa-kendall-stats/
Classifier: Programming Language :: Python :: 3
Classifier: License :: OSI Approved :: GNU Lesser General Public License v3 or later (LGPLv3+)
Classifier: Operating System :: OS Independent
Requires-Python: >=3.11
License-File: LICENSE
Requires-Dist: pandas>=2.0.3
Requires-Dist: numpy>=1.25.2
Requires-Dist: matplotlib>=3.7.2
Requires-Dist: scipy>=1.11.2
Requires-Dist: tables>=3.8.0
Dynamic: license-file
